{
    "items": [
        {
            "width": 16,
            "height": 16,
            "originPosition": {
                "x": 0.0,
                "y": 0.0,
                "z": 0.0
            },
            "tilesets": [],
            "entities": [],
            "colliders": [
                {
                    "tag": "",
                    "points": [
                        {
                            "x": 38.461647033691409,
                            "y": 26.059791564941408
                        },
                        {
                            "x": 12.313833236694336,
                            "y": 67.4940414428711
                        },
                        {
                            "x": 122.93922424316406,
                            "y": 73.93042755126953
                        },
                        {
                            "x": 38.461647033691409,
                            "y": 26.059791564941408
                        }
                    ]
                }
            ]
        },
        {
            "width": 16,
            "height": 16,
            "originPosition": {
                "x": 0.0,
                "y": 0.0,
                "z": 0.0
            },
            "tilesets": [],
            "entities": [],
            "colliders": []
        }
    ]
}